<?xml version="1.0" encoding="UTF-8"?>
<document filename="POD_1259.xml">
	<figureRegion>
		<Coords points="161,692 490,692 161,971 490,971"/>
	</figureRegion>
	<figureRegion>
		<Coords points="117,500 272,500 117,543 272,543"/>
	</figureRegion>
	<figureRegion>
		<Coords points="297,478 490,478 297,576 490,576"/>
	</figureRegion>
	<figureRegion>
		<Coords points="602,129 916,129 602,353 916,353"/>
	</figureRegion>
	<figureRegion>
		<Coords points="287,123 599,123 287,352 599,352"/>
	</figureRegion>
	<figureRegion>
		<Coords points="116,123 285,123 116,352 285,352"/>
	</figureRegion>
</document>